PLEASE/LEEMFUNCTIONS.py
PLEASE/__init__.py
PLEASE/blines.py
PLEASE/config_widget.py
PLEASE/countminimaMT2.py
PLEASE/data.py
PLEASE/detect_peaks.py
PLEASE/experiment.py
PLEASE/externalwindow.py
PLEASE/gendatwidget.py
PLEASE/genericthread.py
PLEASE/gui.py
PLEASE/ipyembed.py
PLEASE/main.py
PLEASE/qthreads.py
PLEASE/setup.py
PLEASE/styles.py
PLEASE/terminal.py
PLEASE/test-mp.py
PLEASE/tifffile.py
PLEASE/icons/pLEASE.png
PLEASE-0.9.8.data/scripts/please.pyw
PLEASE-0.9.8.dist-info/DESCRIPTION.rst
PLEASE-0.9.8.dist-info/METADATA
PLEASE-0.9.8.dist-info/RECORD
PLEASE-0.9.8.dist-info/WHEEL
PLEASE-0.9.8.dist-info/metadata.json
PLEASE-0.9.8.dist-info/top_level.txt
