Metadata-Version: 2.0
Name: PLEASE
Version: 0.9.8
Summary: Software for the analysis of Low Energy Electron Microscopy data
Home-page: https://github.com/mgrady3/pLEASE
Author: Maxwell Grady
Author-email: max.grady@gmail.com
License: GPLv3
Download-URL: https://github.com/mgrady3/pLEASE/archive/master.zip
Keywords: LEEM,LEED,Surface science,Image Analysis,Microscopy,I(V) spectra,Material Science
Platform: any
Classifier: Development Status :: 3 - Alpha
Classifier: Environment :: X11 Applications :: Qt
Classifier: Intended Audience :: Science/Research
Classifier: License :: OSI Approved :: GNU General Public License v3 (GPLv3)
Classifier: Operating System :: OS Independent
Classifier: Programming Language :: Python :: 2.7
Classifier: Programming Language :: Python :: 3
Classifier: Topic :: Scientific/Engineering :: Chemistry
Classifier: Topic :: Scientific/Engineering :: Physics
Classifier: Topic :: Scientific/Engineering :: Visualization
Requires: numpy
Requires: matplotlib
Requires: scipy
Requires: pillow
Requires: pyqt4
Requires: qtconsole
Requires: opencv_python
Requires: pyyaml
Requires: seaborn
Requires: qdarkstyle
Requires: tifffile
